{"trGBnICUVoQ1BQnq2UIT1Q==":"ecom360%20an%20award-winning%20ecom%20agency.svg","RdRODNONbnmCFR3xEUrEKQ==":"more%20then%205m%20sales.svg","lTcSpm1eqHkrxij0mJ5qIw==":"sales%20results-1036x1703.jpg","bgfuUo4cvtj85Zj1mrekiw==":"sales%20results-1440x2367.jpg","8J8cIVtTurIaKoqE/FlFCw==":"more%20then%205m%20sales-2342x1175.png","lANPdVPg22RAsU1mZGml9Q==":"shopify%20sales...!-1256x1110.jpg","6K8VeIiU4X4tvUV1Ko4p2w==":"sales%20results-1256x2065.jpeg","Z3pap3abWaEFy2ngdxA/zg==":"sales%20results-1256x2065.jpeg","Sj1hFtvlbV6X0TH7oVx7/A==":"we%20launch%20&%20scale%20ecom%20stores!-2000x1003.png","7pqrRyEH94mu+fjQloahhw==":"screenshot%202024-02-13%20201608.svg","2PGM8RCq0hv8Ckt1g8hrJg==":"we%20launch%20&%20scale%20ecom%20stores!-2000x1003.png","TuNcUyK8vKsWQHl/tYG6Ig==":"we%20launch%20&%20scale%20ecom%20stores!-2000x1003.png","7SZAMkh20Dk4iDxUrtKLYQ==":"we%20launch%20&%20scale%20ecom%20stores!-2000x1003.png","ZHiYHGSJ2PvdmfhT8MxPvw==":"1.svg","qotB2iZXSukklN7DhxTvNQ==":"2.svg","xRMsRQtPo+tsWRKRi7OGFg==":"3.svg","X3sGIikHZYo4MPljkhZ14w==":"4.svg","/rjAZJ8AFIiUhssMJHTyOQ==":"gallery03.jpg","qWG+T2RNJaluNKMhzXtxew==":"gallery04.jpg","oh4sfGdizJrjHM2Yr79uzA==":"gallery05.jpg","g+A1nw16Joao01SPwnFIaQ==":"gallery07.jpg","O7Ix5WiPC5KQGR5Sc5XdJg==":"gallery02.jpg","ujVfO4bUA8SuzsiqJ6w0ag==":"gallery06.jpg","XqStexa3ucYeWEdbgE9USg==":"background1.jpg","aYA3me8F9ML2cOeBRE+fUg==":"gallery01.jpg","5H+G9LgXulvIaMMKfOy/6w==":"5.svg","w2FkKRGEUCGOwlRRa/ahQw==":"client%20stats-569x483.png","Bw0e5mrYJUkDC03C4huDlQ==":"client%20stats-569x483.png","XINw1LPLQrYS84JAG5X5rA==":"2-1.svg","DpwN1dSdCKXFXEUOcNV6tw==":"shopifyexpert-1896x749.png","LWxCop1Mg95nhu2ZomTr5A==":"shopifyexpert-1-1896x749.png","z3q4FkLOb8bVGjoRe27EbQ==":"www.shopify.ecom360.top.png","A9wfWMPjwrxUkKX2vW9hKw==":"shopifyexpert.svg"}